chaps/__init__.py
chaps/configparser.py
chaps/scope/__init__.py
chaps/scope/instance.py
chaps/scope/singleton.py
chaps/scope/thread.py
chaps-0.5.2.dist-info/DESCRIPTION.rst
chaps-0.5.2.dist-info/METADATA
chaps-0.5.2.dist-info/RECORD
chaps-0.5.2.dist-info/WHEEL
chaps-0.5.2.dist-info/metadata.json
chaps-0.5.2.dist-info/top_level.txt
samples/__init__.py
samples/class_decorator.py
samples/factory.py
samples/instance_properties36.py
samples/simple.py
samples/simple36.py
samples/thread_scope.py
samples/autodiscover/__init__.py
samples/autodiscover/sample.py
samples/autodiscover/services/__init__.py
samples/autodiscover/services/bases.py
samples/autodiscover/services/implementations.py
samples/autodiscover/services/deep/__init__.py
samples/autodiscover/services/deep/implementation/__init__.py
samples/autodiscover/services/deep/implementation/extra_pump.py
samples/autodiscover_profiles/__init__.py
samples/autodiscover_profiles/sample.py
samples/autodiscover_profiles/services/__init__.py
samples/autodiscover_profiles/services/bases.py
samples/autodiscover_profiles/services/implementations.py
samples/autodiscover_profiles/services/deep/__init__.py
samples/autodiscover_profiles/services/deep/implementation/__init__.py
samples/autodiscover_profiles/services/deep/implementation/extra_pump.py
