Metadata-Version: 2.0
Name: chaps
Version: 0.5.2
Summary: Simple DI Library
Home-page: https://github.com/ekiro/chaps
Author: Piotr Karkut
Author-email: karkucik@gmail.com
License: MIT License
Platform: any
Classifier: License :: OSI Approved :: MIT License
Classifier: Programming Language :: Python
Classifier: Programming Language :: Python :: 3.6
Classifier: Operating System :: OS Independent
Classifier: Topic :: Software Development
Classifier: Intended Audience :: Developers
Classifier: Development Status :: 4 - Beta
